hdt.cpython-36m-darwin.so
hdt-2.0.dist-info/LICENSE
hdt-2.0.dist-info/METADATA
hdt-2.0.dist-info/WHEEL
hdt-2.0.dist-info/top_level.txt
hdt-2.0.dist-info/RECORD
