Metadata-Version: 2.1
Name: hdt
Version: 2.0
Summary: Read and query HDT document with ease in Python
Home-page: https://github.com/Callidon/pyHDT
Author: Thomas Minier
Author-email: thomas.minier@univ-nantes.fr
License: MIT
Keywords: hdt,rdf,semantic web,search
Platform: UNKNOWN
Requires-Dist: pybind11 (==2.2.4)
